{
  "version": "7.0.0",
  "description": "Algorand on Metamask",
  "proposedName": "algorand",
  "repository": {
    "type": "git",
    "url": "https://github.com/paulfears/snapalgo.git"
  },
  "source": {
    "shasum": "WgS7k5hc5OvO64SFGty+oVthLAAAQbX6NRFSEmGj2WM=",
    "location": {
      "npm": {
        "filePath": "dist/bundle.js",
        "iconPath": "images/logo.svg",
        "packageName": "algorand",
        "registry": "https://registry.npmjs.org"
      }
    }
  },
  "initialPermissions": {
    "snap_dialog": {},
    "endowment:network-access": {},
    "snap_getBip44Entropy": [
      {
        "coinType": 283
      }
    ],
    "snap_notify": {},
    "snap_manageState": {},
    "endowment:long-running": {},
    "endowment:rpc": {
      "dapps": true,
      "snaps": false
    },
    "endowment:ethereum-provider": {}
  },
  "manifestVersion": "0.1"
}
